[
  {
    "repo": "OpenGeodeWeb-Microservice",
    "python": "opengeodeweb-microservice",
    "version": "1.0.11"
  },
  {
    "repo": "OpenGeodeWeb-Back",
    "python": "opengeodeweb-back",
    "version": "5.14.3"
  },
  {
    "repo": "OpenGeodeWeb-Viewer",
    "python": "opengeodeweb-viewer",
    "version": "1.13.2"
  },
  {
    "repo": "OpenGeodeWeb-Front",
    "version": "10.0.6"
  },
  {
    "repo": "Vease-Back",
    "python": "vease-back",
    "version": "1.7.2"
  },
  {
    "repo": "Vease-Viewer",
    "python": "vease-viewer",
    "version": "2.4.0"
  },
  {
    "repo": "Vease",
    "version": "1.17.5"
  },
  {
    "repo": "PEGGHy-Back",
    "python": "pegghy-back",
    "version": "1.0.4"
  },
  {
    "repo": "PEGGHy-Viewer",
    "python": "pegghy-viewer",
    "version": "1.0.1"
  },
  {
    "repo": "PEGGHy",
    "version": "1.0.8"
  }
]